{
  "file": "618_151_46_Ced_1533_0119701689655158.pdf",
  "text": "--- PAGE 1 ---\nCÉDULA DE\nIDENTIDAD\nEXTRANJERO\nREPUBLICA DE CHILE\nSERVICIO DE SEGISTIC CIVILE IDENTIFICACION\nAPELLIDOS\nAVRIL\nRUN 26.252.359-4\nNOMBRES\nLEON\nNACIONALIDAD\nHTI\nFECHA DE NAC\nNEXO\nM\nDOCUMENTO\n16 MAR 1983 602.521.062\nFECHA DE MON\nFECHA DE VENCIMIENT\n06 NOV 2020 14 OCT 2025\nFIRMA DEL TITULAR\nRILLE\nVisa:\nPERMANENCIA DEFINITIVA\nProfesión: No informada\n2FAZO-2F\nIECHL6025210626s33<<<\n8303165M2510147HTI26252359<4<4\nAVRIL<<LEON<<<<<\nTelefono: 936943027\ncomeo: avrilleon37a@gmail.com",
  "label": "Cedula_identidad",
  "score": 0.16666666666666666,
  "evidence": [
    "\\brun\\b"
  ],
  "processed_at": "2025-12-24T10:44:46",
  "classified_at": "2025-12-24T11:59:41"
}